ipyannotate/__init__.py
ipyannotate/_version.py
ipyannotate/annotation.py
ipyannotate/api.py
ipyannotate/buttons.py
ipyannotate/canvas.py
ipyannotate/colors.py
ipyannotate/progress.py
ipyannotate/shortcut.py
ipyannotate/tasks.py
ipyannotate/toolbar.py
ipyannotate/utils.py
ipyannotate/widget.py
ipyannotate/static/extension.js
ipyannotate/static/index.js
ipyannotate/static/index.js.map
ipyannotate-0.1.0b0.data/data/etc/jupyter/nbconfig/notebook.d/ipyannotate.json
ipyannotate-0.1.0b0.data/data/share/jupyter/nbextensions/ipyannotate/extension.js
ipyannotate-0.1.0b0.data/data/share/jupyter/nbextensions/ipyannotate/index.js
ipyannotate-0.1.0b0.data/data/share/jupyter/nbextensions/ipyannotate/index.js.map
ipyannotate-0.1.0b0.dist-info/DESCRIPTION.rst
ipyannotate-0.1.0b0.dist-info/METADATA
ipyannotate-0.1.0b0.dist-info/RECORD
ipyannotate-0.1.0b0.dist-info/WHEEL
ipyannotate-0.1.0b0.dist-info/metadata.json
ipyannotate-0.1.0b0.dist-info/top_level.txt
