Metadata-Version: 2.0
Name: ipyannotate
Version: 0.1.0b0
Summary: Jupyter Widget for data annotation
Home-page: https://github.com/alexanderkuk/ipyannotate
Author: Alexander Kukushkin
Author-email: alex@alexkuk.ru
License: UNKNOWN
Keywords: ipython,jupyter,widgets
Platform: UNKNOWN
Classifier: Development Status :: 4 - Beta
Classifier: Framework :: IPython
Classifier: Intended Audience :: Developers
Classifier: Intended Audience :: Science/Research
Classifier: Topic :: Multimedia :: Graphics
Classifier: Programming Language :: Python :: 2
Classifier: Programming Language :: Python :: 2.7
Classifier: Programming Language :: Python :: 3
Classifier: Programming Language :: Python :: 3.3
Classifier: Programming Language :: Python :: 3.4
Classifier: Programming Language :: Python :: 3.5
Requires-Dist: ipywidgets (>=7.0.0)
